schemasorter/__init__.py
schemasorter/engine.py
schemasorter-0.1.0.dist-info/METADATA
schemasorter-0.1.0.dist-info/WHEEL
schemasorter-0.1.0.dist-info/licenses/LICENSE
schemasorter-0.1.0.dist-info/RECORD
