Metadata-Version: 2.3
Name: schemasorter
Version: 0.1.0
Summary: Sort SQL table definitions topologically based on foreign key dependencies
Project-URL: Home, https://github.com/siddarta-weis/SchemaSorter
Project-URL: Source, https://github.com/siddarta-weis/SchemaSorter
Project-URL: Tracker, https://github.com/siddarta-weis/SchemaSorter/issues
Requires-Python: >=3.12
Requires-Dist: sqlparse~=0.5.2
